aiopes/__init__.py
aiopes/base.py
aiopes/exceptions.py
aiopes/misc.py
aiopes/resources.py
aiopes/routes.py
aiopes/server.py
aiopes/validate.py
aiopes/wrapped_requests.py
aiopes/models/files.py
aiopes/models/gamemodes.py
aiopes/models/history.py
aiopes/models/locations.py
aiopes/models/logs.py
aiopes/models/mapgroups.py
aiopes/models/players.py
aiopes/models/server.py
aiopes/models/version.py
aiopes-1.0.0.dist-info/LICENSE
aiopes-1.0.0.dist-info/METADATA
aiopes-1.0.0.dist-info/WHEEL
aiopes-1.0.0.dist-info/top_level.txt
aiopes-1.0.0.dist-info/RECORD
