Metadata-Version: 2.1
Name: aiopes
Version: 1.0.0
Summary: Asynchronous wrapper for Pacifices Cloud.
Home-page: https://github.com/WardPearce/aiopes
Author: WardPearce
Author-email: wardpearce@protonmail.com
License: GPL v3
Platform: UNKNOWN
Requires-Python: >=3.6
Requires-Dist: aiohttp (>=3.6.2)
